vestpackage/__init__.py
vestpackage/__main__.py
vestpackage/replace_package.py
vestpackage-1.0.8.dist-info/LICENSE
vestpackage-1.0.8.dist-info/METADATA
vestpackage-1.0.8.dist-info/WHEEL
vestpackage-1.0.8.dist-info/entry_points.txt
vestpackage-1.0.8.dist-info/top_level.txt
vestpackage-1.0.8.dist-info/RECORD
